patientMatcher/__init__.py
patientMatcher/__version__.py
patientMatcher/auth/__init__.py
patientMatcher/auth/auth.py
patientMatcher/cli/__init__.py
patientMatcher/cli/add.py
patientMatcher/cli/commands.py
patientMatcher/cli/remove.py
patientMatcher/cli/update.py
patientMatcher/constants/__init__.py
patientMatcher/instance/__init__.py
patientMatcher/instance/config.py
patientMatcher/match/__init__.py
patientMatcher/match/genotype_matcher.py
patientMatcher/match/handler.py
patientMatcher/match/phenotype_matcher.py
patientMatcher/parse/__init__.py
patientMatcher/parse/patient.py
patientMatcher/resources/__init__.py
patientMatcher/resources/api.json
patientMatcher/resources/benchmark_patients.json
patientMatcher/resources/hp.obo.txt
patientMatcher/resources/phenotype.hpoa
patientMatcher/server/__init__.py
patientMatcher/server/auto.py
patientMatcher/server/controllers.py
patientMatcher/server/extensions.py
patientMatcher/server/views.py
patientMatcher/server/static/favicon.ico
patientMatcher/server/templates/index.html
patientMatcher/utils/__init__.py
patientMatcher/utils/add.py
patientMatcher/utils/delete.py
patientMatcher/utils/disease.py
patientMatcher/utils/ensembl_rest_client.py
patientMatcher/utils/gene.py
patientMatcher/utils/hpo.py
patientMatcher/utils/notify.py
patientMatcher/utils/patient.py
patientMatcher/utils/stats.py
patientMatcher/utils/update.py
patientMatcher/utils/variant.py
patientmatcher-4.6.1.dist-info/METADATA
patientmatcher-4.6.1.dist-info/WHEEL
patientmatcher-4.6.1.dist-info/entry_points.txt
patientmatcher-4.6.1.dist-info/licenses/LICENSE
patientmatcher-4.6.1.dist-info/RECORD
